simpleandfunnycalculator/__init__.py
simpleandfunnycalculator-0.0.5.dist-info/LICENSE.txt
simpleandfunnycalculator-0.0.5.dist-info/METADATA
simpleandfunnycalculator-0.0.5.dist-info/WHEEL
simpleandfunnycalculator-0.0.5.dist-info/top_level.txt
simpleandfunnycalculator-0.0.5.dist-info/RECORD
