Metadata-Version: 2.1
Name: simpleandfunnycalculator
Version: 0.0.5
Summary: Time series classification using Deep Learning
Home-page: UNKNOWN
Author: JavidanAbdullayev (Javidan Abdullayev)
Author-email: <javidan.abdullayev@uha.fr>
License: UNKNOWN
Platform: UNKNOWN
Classifier: Development Status :: 1 - Planning
Classifier: Intended Audience :: Developers
Classifier: Programming Language :: Python :: 3
Classifier: Operating System :: Unix
Classifier: Operating System :: MacOS :: MacOS X
Classifier: Operating System :: Microsoft :: Windows
Requires-Dist: numpy
Requires-Dist: os
Requires-Dist: pandas
